dypy/__init__.py
dypy/core/__init__.py
dypy/core/evaluate.py
dypy/core/functions.py
dypy/core/get_value.py
dypy/core/set_value.py
dypy/core/types.py
dypy/core/utils.py
dypy/wrappers/__init__.py
dypy/wrappers/field_wrapper.py
dypy/wrappers/full_wrapper.py
dypy/wrappers/method_wrapper.py
dypy/wrappers/utils.py
dypy-0.0.7.dist-info/LICENSE
dypy-0.0.7.dist-info/METADATA
dypy-0.0.7.dist-info/WHEEL
dypy-0.0.7.dist-info/top_level.txt
dypy-0.0.7.dist-info/RECORD
