Metadata-Version: 2.1
Name: dypy
Version: 0.0.7
Summary: A toolset for dynamic python code manipulations
Home-page: https://github.com/vahidzee/dypy
Author: Vahid Zehtab, Hamid Kamkari
Author-email: vahid@zehtab.me, hamidrezakamkari@gmail.com
License: MIT
Keywords: dynamic coding,dynamic functions,lazy evaluation
Platform: UNKNOWN
Classifier: Development Status :: 3 - Alpha
Classifier: Intended Audience :: Developers
Classifier: Intended Audience :: End Users/Desktop
Classifier: Intended Audience :: Education
Classifier: Programming Language :: Python :: Implementation
Classifier: License :: OSI Approved :: MIT License
Classifier: Programming Language :: Python :: 3
Classifier: Programming Language :: Python :: 3.8
Classifier: Programming Language :: Python :: 3.9
Classifier: Programming Language :: Python :: 3.10
Classifier: Operating System :: OS Independent
Classifier: Topic :: Software Development :: Libraries :: Python Modules
Classifier: Topic :: Software Development :: Libraries
Classifier: Topic :: Utilities
Requires-Python: >=3.8
